{
  "metadata": {
    "title": "Friday, 13th July, 2012",
    "source_url": "https://www.parliament.gov.zm/node/1879",
    "document_type": "Order Paper",
    "parliament": "NATIONAL ASSEMBLY OF ZAMBIA",
    "session": "FIRST SESSION OF THE ELEVENTH ASSEMBLY",
    "date": "FRIDAY, 13TH JULY, 2012",
    "time": "AT 0900 HOURS"
  },
  "questions": [
    {
      "question_number": "486",
      "asked_by": "Mr Mwango (Kanchibiya)",
      "minister": "Minister of Transport, Works, Supply and Communication",
      "section": "QUESTIONS FOR ORAL ANSWER",
      "parts": [
        "(a)    when the upgrading of the following roads to bituminous standard will be completed:",
        "(i)    Pedicle road; (ii)    Mporokoso-Kaputa road; and (iii)    Nakonde-Mbala road;",
        "(b)    whether the contractors working on the roads at (a) above are carrying out the works in accordance with their contracts; and",
        "(c)    what contribution, if any, the Democratic Republic of Congo has made towards the tarring of the Pedicle road."
      ]
    },
    {
      "question_number": "487",
      "asked_by": "Mr Chisala (Chilubi)",
      "minister": "Minister of Home Affairs",
      "section": "QUESTIONS FOR ORAL ANSWER",
      "parts": [
        "(a)    what the categories of prisons in Zambia were as of 31st December, 2011; and",
        "(b)    which category had the most and the least number of prisoners as of 31st March, 2011."
      ]
    },
    {
      "question_number": "488",
      "asked_by": "Mr Zimba (Kapiri-Mposhi)",
      "minister": "Minister of Home Affairs when a police post in Chief Ngabwe’s area of Kapiri-Mposhi Parliamentary Constituency will be constructed.",
      "section": "QUESTIONS FOR ORAL ANSWER",
      "parts": []
    },
    {
      "question_number": "489",
      "asked_by": "Mr Ntundu (Gwembe)",
      "minister": "Minister of Finance and National Planning how much money was collected by the Zambia Revenue Authority from 1st January, 2011 to 31st December, 2011, in form of the following taxes",
      "section": "QUESTIONS FOR ORAL ANSWER",
      "parts": [
        "(a)    Excise Duty;",
        "(b)    Customs Duty;",
        "(c)    Value Added Tax;",
        "(d)    Pay As You Earn; and",
        "(e)    other taxes."
      ]
    },
    {
      "question_number": "490",
      "asked_by": "Mr Mbulakulima (Chembe)",
      "minister": "Minister of Local Government and Housing when the Government will modernise the Milenge Market in Milenge District.",
      "section": "QUESTIONS FOR ORAL ANSWER",
      "parts": []
    },
    {
      "question_number": "491",
      "asked_by": "Mr Kalaba (Bahati)",
      "minister": "Minister of Youth and Sport whether the Government has any plans for youth development and, if so, what the plans are.",
      "section": "QUESTIONS FOR ORAL ANSWER",
      "parts": []
    },
    {
      "question_number": "492",
      "asked_by": "Mr Milambo (Mwembeshi)",
      "minister": "Minister of Transport, Works, Supply and Communication",
      "section": "QUESTIONS FOR ORAL ANSWER",
      "parts": [
        "(a)    whether the Ministry has any plans to upgrade the Nampundwe-Nalubanda road to bituminous standard;",
        "(b)    if so, when the project will begin; and",
        "(c)    if not, why."
      ]
    },
    {
      "question_number": "493",
      "asked_by": "Mr Sianga (Sesheke)",
      "minister": "Minister of Transport, Works, Supply and Communication",
      "section": "QUESTIONS FOR ORAL ANSWER",
      "parts": [
        "(a)    whether the Government has any plans to rehabilitate the Livingstone-Sesheke Road; and",
        "(b)    if so, when the exercise will commence."
      ]
    },
    {
      "question_number": "494",
      "asked_by": "Mr Chingimbu (Kabompo East)",
      "minister": "Minister of Education, Science, Vocational Training and Early Education what the minimum requirements for upgrading a basic school to a high school are.",
      "section": "QUESTIONS FOR ORAL ANSWER",
      "parts": []
    },
    {
      "question_number": "495",
      "asked_by": "Mr Mushanga (Bwacha)",
      "minister": "Minister of Transport, Works, Supply",
      "section": "QUESTIONS FOR ORAL ANSWER",
      "parts": [
        "(a)    when Buntungwa Industrial Road in Kabwe, which links the town centre to Ngungu Compound, will be rehabilitated; and",
        "(b)    when the township roads in Bwacha Parliamentary Constituency, which are in a deplorable state, will be rehabilitated."
      ],
      "question_text": " and Communication:"
    },
    {
      "question_number": "496",
      "asked_by": "Mr Miyutu (Kalabo Central)",
      "minister": "Minister of Agriculture and Livestock",
      "section": "QUESTIONS FOR ORAL ANSWER",
      "parts": [
        "(a)    what the source of black leg disease which has killed a lot of cattle in Kalabo District is;",
        "(b)    when the Government will provide drugs to contain the disease in the District; and",
        "(c)    when agricultural camps will be provided with staff."
      ]
    },
    {
      "question_number": "497",
      "asked_by": "Mr Siamunene (Sinazongwe)",
      "minister": "Minister of Transport, Works, Supply and Communication when the road to the new Namafulu Border Post in Sinanzongwe District will be constructed.",
      "section": "QUESTIONS FOR ORAL ANSWER",
      "parts": []
    },
    {
      "question_number": "498",
      "asked_by": "Mr Antonio (Kaoma Central)",
      "minister": "Minister of Transport, Works, Supply and Communication when the Njonjolo road which leads to Chief Kahare’s Palace in Kaoma District will be rehabilitated.",
      "section": "QUESTIONS FOR ORAL ANSWER",
      "parts": [
        "(a)    how many schools taught the following subjects as of 2011, province by province:",
        "(i)    Technical Drawing; (ii)    Physics; (iii)    Chemistry; (iv)    Biology; and",
        "(v)    Additional Mathematics;",
        "(b)    of the schools above, how many were owned by the following institutions, province by province:",
        "(i)    Government; (ii)    Faith-Based Organisations; and (iii)    Private Sector; and",
        "(c)    whether there had been any increase or decline in the teaching of technical subjects country-wide in the period 1999-2011. W35    Mr Mufalali (Senanga) - to ask the Minister of Education, Science, Vocational Training and Early Education:",
        "(a)    how many pupils qualified to the public universities from 1991 to 2011, province by province;",
        "(b)    how many students dropped out of each university, province by province due to failure to:",
        "(i)    pay the tuition fees; and (ii)    pass the examinations; and",
        "(c)    how many students graduated, in the following fields, province by province, in the period at (a) above:",
        "(i)    medicine; (ii)    engineering; (iii)    economics; and (iv)    education. ORDER OF THE DAY 1    The Civil Aviation Authority Bill                (N.A.B. 7/2012) Second Reading"
      ],
      "question_text": " QUESTIONS FOR WRITTEN ANSWER"
    }
  ],
  "question_count": 13,
  "status": "success"
}